followme/__init__.py
followme/cli.py
followme/core.py
followme-1.0.1.dist-info/licenses/LICENSE
followme-1.0.1.dist-info/METADATA
followme-1.0.1.dist-info/WHEEL
followme-1.0.1.dist-info/entry_points.txt
followme-1.0.1.dist-info/top_level.txt
followme-1.0.1.dist-info/RECORD
