Metadata-Version: 2.4
Name: followme
Version: 1.0.1
Summary: A command-line tool to track and report URL redirects
Author-email: Rapid Rabbit Software <python@rapidrabbit.software>
Maintainer-email: Chris McMichael <python@apprabb.it>
License-Expression: MIT
Project-URL: Homepage, https://github.com/rapidrabbitsoft/followme
Project-URL: Repository, https://github.com/rapidrabbitsoft/followme
Project-URL: Issues, https://github.com/rapidrabbitsoft/followme/issues
Keywords: url,redirect,tracking,command-line,tool
Classifier: Development Status :: 4 - Beta
Classifier: Intended Audience :: Developers
Classifier: Operating System :: OS Independent
Classifier: Programming Language :: Python :: 3
Classifier: Programming Language :: Python :: 3.7
Classifier: Programming Language :: Python :: 3.8
Classifier: Programming Language :: Python :: 3.9
Classifier: Programming Language :: Python :: 3.10
Classifier: Programming Language :: Python :: 3.11
Classifier: Programming Language :: Python :: 3.12
Classifier: Programming Language :: Python :: 3.13
Requires-Python: >=3.7
License-File: LICENSE
Requires-Dist: requests>=2.25.0
Provides-Extra: windows
Requires-Dist: colorama>=0.4.0; extra == "windows"
Dynamic: license-file
